MANIFEST.in
README.md
setup.py
payex/__init__.py
payex/handlers.py
payex/pxagreement.py
payex/pxorder.py
payex/service.py
payex/utils.py
pypayex.egg-info/PKG-INFO
pypayex.egg-info/SOURCES.txt
pypayex.egg-info/dependency_links.txt
pypayex.egg-info/requires.txt
pypayex.egg-info/top_level.txt