Metadata-Version: 1.0
Name: pypayex
Version: 0.4.0
Summary: PayEx API wrapper
Home-page: https://github.com/funkbit/pypayex
Author: Funkbit AS
Author-email: post@funkbit.no
License: BSD
Platform: UNKNOWN
Classifier: Development Status :: 4 - Beta
Classifier: Intended Audience :: Developers
Classifier: License :: OSI Approved :: BSD License
Classifier: Programming Language :: Python
Classifier: Programming Language :: Python :: 2.6
Classifier: Programming Language :: Python :: 2.7
Classifier: Topic :: Software Development :: Libraries :: Python Modules
